sanskritwordnet/__init__.py
sanskritwordnet/sanskritwordnet.py
sanskritwordnet-0.1.0.dist-info/METADATA
sanskritwordnet-0.1.0.dist-info/WHEEL
sanskritwordnet-0.1.0.dist-info/top_level.txt
sanskritwordnet-0.1.0.dist-info/RECORD
