Metadata-Version: 2.1
Name: sanskritwordnet
Version: 0.1.0
Summary: A light-weight Python wrapper for the Sanskrit WordNet API
Home-page: UNKNOWN
Author: William Michael Short
Author-email: w.short@exeter.ac.uk
License: GNU General Public License v3.0
Platform: UNKNOWN
Requires-Dist: requests (>=2.22.0)
Requires-Dist: python-dotenv (>=0.12.0)
